MANIFEST.in
README.md
setup.py
falass/__init__.py
falass/_testutils.py
falass/analysis.py
falass/compare.py
falass/dataformat.py
falass/job.py
falass/readwrite.py
falass/reflect.py
falass/sld.py
falass.egg-info/PKG-INFO
falass.egg-info/SOURCES.txt
falass.egg-info/dependency_links.txt
falass.egg-info/requires.txt
falass.egg-info/top_level.txt
falass/test/__init__.py
falass/test/test.lgt
falass/test/test.pdb
falass/test/test2.dat
falass/test/test2.lgt
falass/test/test2.pdb
falass/test/test3.dat
falass/test/test4.dat
falass/test/test_compare.py
falass/test/test_dataformat.py
falass/test/test_job.py
falass/test/test_readwrite.py
falass/test/test_reflect.py
falass/test/test_sld.py