Metadata-Version: 1.1
Name: falass
Version: 1.0.6
Summary: Neutron and X-ray Reflectometry from Computer Simulation
Home-page: http://people.bath.ac.uk/arm61/falass/
Author: Andrew R. McCluskey
Author-email: arm61@bath.ac.uk
License: MIT
Platform: Windows
Platform: Linux
Platform: Solaris
Platform: Mac OS-X
Platform: Unix
Classifier: Development Status :: 3 - Alpha
Classifier: Intended Audience :: Science/Research
Classifier: Topic :: Scientific/Engineering
Classifier: Topic :: Scientific/Engineering :: Chemistry
Classifier: Topic :: Scientific/Engineering :: Physics
Classifier: Programming Language :: Python :: 3
